LICENSE.txt
README.md
setup.py
cryptomind/__init__.py
cryptomind/app.py
cryptomind/main.py
cryptomind.egg-info/PKG-INFO
cryptomind.egg-info/SOURCES.txt
cryptomind.egg-info/dependency_links.txt
cryptomind.egg-info/entry_points.txt
cryptomind.egg-info/top_level.txt