Metadata-Version: 2.1
Name: cryptomind
Version: 0.0
Summary: Cryptomind is a tool to interact between different cryptocurrencies.
Author: istakshaydilip
License-File: LICENSE.txt
